pipedrive/__init__.py
pipedrive/abstract.py
pipedrive/aio.py
pipedrive/chain.py
pipedrive/errors.py
pipedrive/sio.py
pipedrivepy-1.0.0b0.dist-info/LICENSE
pipedrivepy-1.0.0b0.dist-info/METADATA
pipedrivepy-1.0.0b0.dist-info/WHEEL
pipedrivepy-1.0.0b0.dist-info/top_level.txt
pipedrivepy-1.0.0b0.dist-info/RECORD
