Metadata-Version: 2.1
Name: pipedrivepy
Version: 1.0.0b0
Summary: Pipedrive API Generic Client
Home-page: https://github.com/bindlock/pipedrivepy
Author: Vitalii Maslov
Author-email: hello@bindlock.me
License: MIT
Download-URL: https://github.com/bindlock/pipedrivepy/tarball/master
Keywords: Pipedrive,python,API
Platform: UNKNOWN
Classifier: Environment :: Web Environment
Classifier: Intended Audience :: Developers
Classifier: Programming Language :: Python :: 3
Provides-Extra: async
Requires-Dist: aiohttp ; extra == 'async'
Provides-Extra: sync
Requires-Dist: requests ; extra == 'sync'
